davidkhala/tencent/map/__init__.py
davidkhala_tencent_map-0.0.0.dist-info/METADATA
davidkhala_tencent_map-0.0.0.dist-info/WHEEL
davidkhala_tencent_map-0.0.0.dist-info/RECORD
