Metadata-Version: 2.4
Name: davidkhala.tencent.map
Version: 0.0.0
Requires-Python: >=3.12
Requires-Dist: davidkhala-utils[http-request]
